LICENSE
MANIFEST.in
README.md
setup.py
src/ea/__init__.py
src/ea/sutadapters/__init__.py
src/ea/sutadapters/WEB/__init__.py
src/ea/sutadapters/WEB/curl_http.py
src/ea/sutadapters/WEB/curl_templates.py
src/ea/sutadapters/WEB/deps/pip_list.txt
src/ea/sutadapters/WEB/deps/yum_list.txt
src/ea/var/tests/1/actions/http/curl.yml
src/ea/var/tests/1/deprecated/Samples/Adapter_WEB/001_HTTP_JSON.tpx
src/ea/var/tests/1/deprecated/Samples/Adapter_WEB/001_HTTP_RAW.tpx
src/ea/var/tests/1/deprecated/Samples/Adapter_WEB/001_HTTP_SOAP.tpx
src/ea/var/tests/1/deprecated/Samples/Adapter_WEB/001_httpbin_rest.tpx
src/ea/var/tests/1/deprecated/Samples/Adapter_WEB/001_webservicex_soap.tpx
src/ea/var/tests/1/workflows/http/httpbin.yml
src/ea/var/tests/1/workflows/http/jsonplaceholder.yml
src/extensiveautomation_plugin_web.egg-info/PKG-INFO
src/extensiveautomation_plugin_web.egg-info/SOURCES.txt
src/extensiveautomation_plugin_web.egg-info/dependency_links.txt
src/extensiveautomation_plugin_web.egg-info/requires.txt
src/extensiveautomation_plugin_web.egg-info/top_level.txt