Metadata-Version: 2.1
Name: extensiveautomation-plugin-web
Version: 1.4.0
Summary: WEB plugin for extensiveautomation server
Home-page: https://www.extensiveautomation.org/
Author: Denis MACHARD
Author-email: d.machard@gmail.com
Keywords: extensiveautomation automation testautomation testing plugin
Platform: any
Classifier: License :: OSI Approved :: MIT License
Classifier: Programming Language :: Python :: 3
Classifier: Operating System :: OS Independent
Classifier: Topic :: Software Development :: Testing
Classifier: Topic :: Software Development :: Testing :: Acceptance
License-File: LICENSE
